Workbook

Sheet README
A1: DSP / HCS Staffing Agency — Financial Model
A3: HOW TO USE
A4: - YELLOW cells = inputs you edit. GREEN cells = calculated (don't overwrite).
A5: - Change any yellow input and all dependent green cells recalculate automatically.
A6: - Works in Excel or Google Sheets. Formulas are live.
A8: TABS
A9: 1. Assumptions - all inputs in one place.
A10: 2. Unit Economics - bill vs. pay rate, gross margin per hour, annual P&L.
A11: 3. Working Capital - payroll float: cash gap between paying DSPs and getting paid.
A12: 4. Acquisition - pro-forma for buying an agency (multiple, price, funding, returns).
A14: GROUNDING (Texas / San Antonio, 2025-2026 - verify before relying)
A15: - TX Medicaid attendant rates support avg ~$13.00/hr wage + 14-15% payroll-tax/benefits (Sept 2025).
... A22: These are starting assumptions, not guarantees. Replace with real diligence numbers.

Sheet Assumptions
A1: Assumptions (edit YELLOW cells)
A2: Input | B2: Value | C2: Note
A3: LABOR & BILLING
A4: DSP pay rate ($/hr) | B4: 14 | C4: What you pay the caregiver (~$13 Medicaid avg; pay up to compete).
A5: Bill rate multiplier (x pay) | B5: 1.6 | C5: 1.45-1.75 typical. Medicaid is rate-capped - confirm allowable.
A6: Billable hours per DSP per week | B6: 32 | C6: Net of unfilled shifts, PTO, no-shows.
A7: Number of DSPs (FTE-equiv) | B7: 40 | C7: Drives total volume.
A8: Weeks operating per year | B8: 52
A10: LABOR BURDEN (on top of pay)
A11: Employer payroll taxes (FICA+FUTA+SUTA) % | B11: 0.1 | C11: ~8-12% of wages.
A12: Workers' comp % | B12: 0.05 | C12: 5-15%+ for caregiving. Optional in TX but recommended.
A13: Benefits / PTO % | B13: 0.04 | C13: Raise to compete on retention.
A15: OVERHEAD (fixed, annual)
A16: Office rent + utilities | B16: 36000
A17: Admin & office salaries (non-billable) | B17: 180000 | C17: Administrator, scheduler, biller, recruiter.
A18: Insurance (GL + professional + EPLI) | B18: 12000
A19: Software (EVV, scheduling, payroll) | B19: 9000 | C19: HHAeXchange EVV free for Medicaid; other tools paid.
A20: Compliance, training, licensing | B20: 8000 | C20: HCSSA $2,625/3yr, admin training, background checks.
A21: Marketing & recruiting | B21: 24000 | C21: Recruiting DSPs is the real bottleneck.
A22: Other G&A | B22: 18000
A24: WORKING CAPITAL
A25: Days to collect (Medicaid/MCO) | B25: 45 | C25: 30-90 days typical for Medicaid.
A26: Payroll frequency (days) | B26: 7 | C26: Weekly payroll = bigger float.
A27: Factoring? (1=yes, 0=no) | B27: 0 | C27: If 1, applies factoring lines below.
A28: Factoring advance rate | B28: 0.85 | C28: 70-92% typical.
A29: Factoring annual cost rate | B29: 0.24 | C29: ~18-36% annualized.
A31: ACQUISITION
A32: Target trailing revenue | B32: 1500000 | C32: From seller financials.
A33: Target EBITDA margin | B33: 0.15 | C33: Normalized after market-rate owner salary.
A34: Purchase multiple (x EBITDA) | B34: 5 | C34: Small IDD ~4-7x; platforms 8-11x.
A35: % financed with debt | B35: 0.5 | C35: SBA / seller note / lender.
A36: Debt interest rate | B36: 0.105 | C36: Illustrative.
A37: Equity raise target | B37: 750000 | C37: What you raise from investors.

Sheet Unit Economics
A1: Unit Economics
A2: PER BILLED HOUR
A3: DSP pay rate | B3: ='Assumptions'!B4
A4: Bill rate | B4: ='Assumptions'!B4*'Assumptions'!B5
A5: Labor burden $/hr | B5: ='Assumptions'!B4*('Assumptions'!B11+'Assumptions'!B12+'Assumptions'!B13)
A6: Fully loaded labor cost $/hr | B6: ='Unit Economics'!B3+'Unit Economics'!B5
A7: Gross profit $/hr | B7: ='Unit Economics'!B4-'Unit Economics'!B6
A8: Gross margin % | B8: ='Unit Economics'!B7/'Unit Economics'!B4
A10: ANNUAL VOLUME
A11: Total billable hours / yr | B11: ='Assumptions'!B6*'Assumptions'!B7*'Assumptions'!B8
A13: ANNUAL P&L
A14: Revenue | B14: ='Unit Economics'!B4*'Unit Economics'!B11
A15: Cost of labor (pay + burden) | B15: ='Unit Economics'!B6*'Unit Economics'!B11
A16: Gross profit | B16: ='Unit Economics'!B14-'Unit Economics'!B15
A17: Gross margin % | B17: ='Unit Economics'!B16/'Unit Economics'!B14
A18: Total overhead (fixed) | B18: =SUM('Assumptions'!B16,'Assumptions'!B17,'Assumptions'!B18,'Assumptions'!B19,'Assumptions'!B20,'Assumptions'!B21,'Assumptions'!B22)
A19: EBITDA | B19: ='Unit Economics'!B16-'Unit Economics'!B18
A20: EBITDA margin % | B20: ='Unit Economics'!B19/'Unit Economics'!B14

Sheet Working Capital
A1: Working Capital - Payroll Float
A2: Annual revenue | B2: ='Unit Economics'!B14
A3: Annual labor cost (cash out) | B3: ='Unit Economics'!B15
A4: Avg daily revenue | B4: ='Working Capital'!B2/365
A5: Avg daily labor cost | B5: ='Working Capital'!B3/365
A7: Days to collect from payer | B7: ='Assumptions'!B25
A8: Payroll cycle (days) | B8: ='Assumptions'!B26
A9: Float gap (days) | B9: ='Working Capital'!B7-'Working Capital'!B8
A11: PEAK WORKING CAPITAL NEEDED
A12: AR outstanding (revenue in transit) | B12: ='Working Capital'!B4*'Working Capital'!B7
A13: Labor cash paid out during gap | B13: ='Working Capital'!B5*'Working Capital'!B9
A14: Est. working capital required | B14: =MAX('Working Capital'!B12,'Working Capital'!B13)
A16: IF FACTORING (toggle on Assumptions)
A17: Cash advanced upfront | B17: ='Working Capital'!B12*'Assumptions'!B28*'Assumptions'!B27
A18: Annual factoring cost | B18: ='Working Capital'!B2*'Assumptions'!B29*'Assumptions'!B27

Sheet Acquisition
A1: Acquisition Pro-Forma
A2: TARGET
A3: Trailing revenue | B3: ='Assumptions'!B32
A4: EBITDA margin | B4: ='Assumptions'!B33
A5: EBITDA | B5: ='Acquisition'!B3*'Acquisition'!B4
A7: PURCHASE
A8: Purchase multiple | B8: ='Assumptions'!B34
A9: Enterprise value (purchase price) | B9: ='Acquisition'!B5*'Acquisition'!B8
A11: FUNDING
A12: Debt financed | B12: ='Acquisition'!B9*'Assumptions'!B35
A13: Equity required | B13: ='Acquisition'!B9-'Acquisition'!B12
A14: Equity raise target | B14: ='Assumptions'!B37
A15: Surplus / (shortfall) vs. raise | B15: ='Acquisition'!B14-'Acquisition'!B13
A17: RETURNS (illustrative, pre-tax, year 1, interest-only)
A18: Annual debt service (interest only) | B18: ='Acquisition'!B12*'Assumptions'!B36
A19: EBITDA after debt service | B19: ='Acquisition'!B5-'Acquisition'!B18
A20: Cash-on-cash return on equity | B20: ='Acquisition'!B19/'Acquisition'!B13
A21: Implied payback (yrs on equity) | B21: ='Acquisition'!B13/'Acquisition'!B19
A23: Simplified: interest-only, pre-tax, single year. For a raise, build a 5-yr projection with
A24: census ramp, principal amortization, and taxes.
